kinforge/__init__.py
kinforge/cli.py
kinforge/errors.py
kinforge/compiler/__init__.py
kinforge/compiler/compiled.py
kinforge/compiler/compiler_v0.py
kinforge/compiler/compiler_v1.py
kinforge/exporters/__init__.py
kinforge/exporters/sdf.py
kinforge/exporters/urdf.py
kinforge/model/__init__.py
kinforge/model/assembly.py
kinforge/model/body.py
kinforge/model/frame.py
kinforge/model/graph.py
kinforge/model/instance.py
kinforge/model/joint.py
kinforge/parser/loader.py
kinforge/parser/models_v0.py
kinforge/parser/models_v1.py
kinforge/parser/validator.py
kinforge/schema/__init__.py
kinforge/utils/names.py
kinforge/utils/ordering.py
kinforge/utils/transforms.py
tests/test_cli.py
tests/test_compiled.py
tests/test_compiler.py
tests/test_errors.py
tests/test_exporters.py
tests/test_golden_sdf.py
tests/test_loader.py
tests/test_models.py
tests/test_urdf.py
tests/test_utils.py
kinforge-1.1.1.dist-info/METADATA
kinforge-1.1.1.dist-info/WHEEL
kinforge-1.1.1.dist-info/entry_points.txt
kinforge-1.1.1.dist-info/top_level.txt
kinforge-1.1.1.dist-info/RECORD
