Metadata-Version: 2.4
Name: kinforge
Version: 1.1.1
Summary: Forge robot and world models from structured JSON specs
Author-email: Your Name <you@example.com>
License: Apache-2.0
Project-URL: Homepage, https://github.com/kinforge-dev/kinforge
Requires-Python: >=3.9
Requires-Dist: pydantic
Requires-Dist: defusedxml
Requires-Dist: argcomplete>=3.0.0
Provides-Extra: test
Requires-Dist: pytest>=7.0; extra == "test"
Requires-Dist: pytest-cov>=7.0; extra == "test"
Requires-Dist: pytest-flake8>=7.3.0; extra == "test"
Requires-Dist: pytest-isort>=7.0.0; extra == "test"
Requires-Dist: pytest-black>=25.12.0; extra == "test"
Requires-Dist: pytest-bandit>=1.9.0; extra == "test"
Requires-Dist: pytest-autoflake>=1.0; extra == "test"
